{
 "gene_set_to_genes": {
  "GO_CELL_MIGRATION_INVOLVED_IN_SPROUTING_ANGIOGENESIS": [
   "AKT1",
   "ANXA1",
   "CIB1",
   "EPHB4",
   "FBXW7",
   "FGFBP1",
   "HMOX1",
   "ITGB1",
   "ITGB1BP1",
   "KLF4",
   "NOTCH1",
   "PLK2",
   "RHOA",
   "THBS1",
   "VEGFA"
  ],
  "GO_SPROUTING_ANGIOGENESIS": [
   "ANXA1",
   "CDC42",
   "CIB1",
   "EPN1",
   "FGFBP1",
   "GLUL",
   "ITGB1",
   "JAK1",
   "KLF4",
   "PKM",
   "PLK2",
   "RHOA",
   "RNF213",
   "THBS1",
   "VEGFB"
  ],
  "GO_NEGATIVE_REGULATION_OF_SPROUTING_ANGIOGENESIS": [
   "CARD10",
   "CREB3L1",
   "EPN1",
   "HDAC5",
   "ITGB1BP1",
   "KLF4",
   "MMRN2",
   "NOTCH1",
   "PDCD10",
   "RHOA",
   "SPRED1",
   "THBS1"
  ],
  "GO_LYMPHANGIOGENESIS": [
   "ACVRL1",
   "BMPR2",
   "EPHA2",
   "PDPN",
   "PPP3CB",
   "PTPN14",
   "SOX18"
  ],
  "GO_REGULATION_OF_CELL_MIGRATION_INVOLVED_IN_SPROUTING_ANGIOGENESIS": [
   "ABL1",
   "ANXA1",
   "CIB1",
   "FBXW7",
   "FGFBP1",
   "HDAC7",
   "HMOX1",
   "ITGB1BP1",
   "KLF4",
   "NOTCH1",
   "NRP1",
   "PLK2",
   "RHOA",
   "THBS1",
   "VEGFA"
  ],
  "GO_POSITIVE_REGULATION_OF_SPROUTING_ANGIOGENESIS": [
   "ABL1",
   "ANXA1",
   "CIB1",
   "FGFBP1",
   "HDAC7",
   "HMOX1",
   "ITGA5",
   "JAK1",
   "JMJD8",
   "KLF4",
   "MAP3K3",
   "NRP1",
   "PKM",
   "PLK2",
   "VEGFA"
  ],
  "GO_ANGIOGENESIS_INVOLVED_IN_WOUND_HEALING": [
   "ADIPOR2",
   "B4GALT1",
   "CD34",
   "DAG1",
   "ETS1",
   "GPX1",
   "HPSE",
   "MCAM",
   "PIK3CB",
   "PRCP",
   "SERPINE1",
   "SRF",
   "XBP1"
  ],
  "GO_REGULATION_OF_SPROUTING_ANGIOGENESIS": [
   "ANXA1",
   "CIB1",
   "EPN1",
   "FGFBP1",
   "GLUL",
   "HMOX1",
   "ITGA5",
   "ITGB1BP1",
   "JAK1",
   "KLF4",
   "NOTCH1",
   "PKM",
   "PLK2",
   "RHOA",
   "THBS1"
  ],
  "GO_BLOOD_VESSEL_ENDOTHELIAL_CELL_PROLIFERATION_INVOLVED_IN_SPROUTING_ANGIOGENESIS": [
   "ACVRL1",
   "EPHA2",
   "FGFBP1",
   "HMOX1",
   "ITGB1BP1",
   "PDCD10",
   "THBS1",
   "VEGFA"
  ],
  "GO_POSITIVE_REGULATION_OF_CELL_MIGRATION_INVOLVED_IN_SPROUTING_ANGIOGENESIS": [
   "ABL1",
   "ANXA1",
   "CIB1",
   "FGFBP1",
   "HDAC7",
   "HMOX1",
   "MAP3K3",
   "NRP1",
   "PIK3C2A",
   "PLK2",
   "VEGFA"
  ],
  "GO_NEGATIVE_REGULATION_OF_CELL_MIGRATION_INVOLVED_IN_SPROUTING_ANGIOGENESIS": [
   "CARD10",
   "HDAC5",
   "ITGB1BP1",
   "KLF4",
   "MMRN2",
   "NOTCH1",
   "PDCD10",
   "RHOA",
   "SPRED1",
   "THBS1"
  ]
 },
 "gene_set_to_pval": {
  "GO_CELL_MIGRATION_INVOLVED_IN_SPROUTING_ANGIOGENESIS": 0.0966183574879227,
  "GO_SPROUTING_ANGIOGENESIS": 0.03372681281618887,
  "GO_NEGATIVE_REGULATION_OF_SPROUTING_ANGIOGENESIS": 0.06920415224913495,
  "GO_LYMPHANGIOGENESIS": 0.8,
  "GO_REGULATION_OF_CELL_MIGRATION_INVOLVED_IN_SPROUTING_ANGIOGENESIS": 0.0009,
  "GO_POSITIVE_REGULATION_OF_SPROUTING_ANGIOGENESIS": 0.03215434083601286,
  "GO_ANGIOGENESIS_INVOLVED_IN_WOUND_HEALING": 0.425531914893617,
  "GO_REGULATION_OF_SPROUTING_ANGIOGENESIS": 0.03937007874015748,
  "GO_BLOOD_VESSEL_ENDOTHELIAL_CELL_PROLIFERATION_INVOLVED_IN_SPROUTING_ANGIOGENESIS": 0.6451612903225806,
  "GO_POSITIVE_REGULATION_OF_CELL_MIGRATION_INVOLVED_IN_SPROUTING_ANGIOGENESIS": 0.011514104778353483,
  "GO_NEGATIVE_REGULATION_OF_CELL_MIGRATION_INVOLVED_IN_SPROUTING_ANGIOGENESIS": 0.14492753623188406
 },
 "gene_set_to_pairwise_pvals": {
  "GO_SPROUTING_ANGIOGENESIS": {
   "ANXA1,CDC42": 0.5405405405405406,
   "ANXA1,CIB1": 0.02,
   "ANXA1,EPN1": 0.8333333333333334,
   "ANXA1,FGFBP1": 0.001,
   "ANXA1,GLUL": 0.014,
   "ANXA1,ITGB1": 0.4444444444444444,
   "ANXA1,JAK1": 0.2857142857142857,
   "ANXA1,KLF4": 0.0711743772241993,
   "ANXA1,PKM": 0.6451612903225806,
   "ANXA1,PLK2": 0.2564102564102564,
   "ANXA1,RHOA": 0.46511627906976744,
   "ANXA1,RNF213": 0.2564102564102564,
   "ANXA1,THBS1": 0.005,
   "ANXA1,VEGFB": 0.07782101167315175,
   "CDC42,CIB1": 0.003,
   "CDC42,EPN1": 0.014,
   "CDC42,FGFBP1": 0.008,
   "CDC42,GLUL": 0.6666666666666666,
   "CDC42,ITGB1": 0.015,
   "CDC42,JAK1": 0.5263157894736842,
   "CDC42,KLF4": 0.9090909090909091,
   "CDC42,PKM": 0.06968641114982578,
   "CDC42,PLK2": 0.8,
   "CDC42,RHOA": 0.16,
   "CDC42,RNF213": 0.7142857142857143,
   "CDC42,THBS1": 0.3508771929824561,
   "CDC42,VEGFB": 0.5405405405405406,
   "CIB1,EPN1": 0.5555555555555556,
   "CIB1,FGFBP1": 0.3448275862068966,
   "CIB1,GLUL": 0.37735849056603776,
   "CIB1,ITGB1": 0.07518796992481203,
   "CIB1,JAK1": 0.19047619047619047,
   "CIB1,KLF4": 0.5882352941176471,
   "CIB1,PKM": 1.0,
   "CIB1,PLK2": 0.012,
   "CIB1,RHOA": 0.6060606060606061,
   "CIB1,RNF213": 0.002,
   "CIB1,THBS1": 0.11494252873563218,
   "CIB1,VEGFB": 0.6896551724137931,
   "EPN1,FGFBP1": 0.8,
   "EPN1,GLUL": 0.3333333333333333,
   "EPN1,ITGB1": 0.2127659574468085,
   "EPN1,JAK1": 0.07142857142857142,
   "EPN1,KLF4": 0.17391304347826086,
   "EPN1,PKM": 0.6451612903225806,
   "EPN1,PLK2": 0.30303030303030304,
   "EPN1,RHOA": 0.5882352941176471,
   "EPN1,RNF213": 0.19801980198019803,
   "EPN1,THBS1": 0.06535947712418301,
   "EPN1,VEGFB": 0.5263157894736842,
   "FGFBP1,GLUL": 0.04219409282700422,
   "FGFBP1,ITGB1": 0.8,
   "FGFBP1,JAK1": 0.7407407407407407,
   "FGFBP1,KLF4": 0.15873015873015872,
   "FGFBP1,PKM": 0.3333333333333333,
   "FGFBP1,PLK2": 0.47619047619047616,
   "FGFBP1,RHOA": 0.46511627906976744,
   "FGFBP1,RNF213": 0.15151515151515152,
   "FGFBP1,THBS1": 0.9090909090909091,
   "FGFBP1,VEGFB": 0.17094017094017094,
   "GLUL,ITGB1": 0.32786885245901637,
   "GLUL,JAK1": 0.47619047619047616,
   "GLUL,KLF4": 0.05555555555555555,
   "GLUL,PKM": 0.8333333333333334,
   "GLUL,PLK2": 0.4166666666666667,
   "GLUL,RHOA": 0.40816326530612246,
   "GLUL,RNF213": 0.21739130434782608,
   "GLUL,THBS1": 0.4,
   "GLUL,VEGFB": 0.8333333333333334,
   "ITGB1,JAK1": 0.18691588785046728,
   "ITGB1,KLF4": 0.9090909090909091,
   "ITGB1,PKM": 0.003,
   "ITGB1,PLK2": 0.8695652173913043,
   "ITGB1,RHOA": 0.6666666666666666,
   "ITGB1,RNF213": 0.7142857142857143,
   "ITGB1,THBS1": 0.4,
   "ITGB1,VEGFB": 0.7692307692307693,
   "JAK1,KLF4": 0.9523809523809523,
   "JAK1,PKM": 0.21052631578947367,
   "JAK1,PLK2": 0.9090909090909091,
   "JAK1,RHOA": 0.5714285714285714,
   "JAK1,RNF213": 0.8333333333333334,
   "JAK1,THBS1": 0.8333333333333334,
   "JAK1,VEGFB": 0.8695652173913043,
   "KLF4,PKM": 0.8695652173913043,
   "KLF4,PLK2": 0.3389830508474576,
   "KLF4,RHOA": 0.38461538461538464,
   "KLF4,RNF213": 0.5555555555555556,
   "KLF4,THBS1": 0.6666666666666666,
   "KLF4,VEGFB": 0.625,
   "PKM,PLK2": 0.3389830508474576,
   "PKM,RHOA": 0.5882352941176471,
   "PKM,RNF213": 0.5714285714285714,
   "PKM,THBS1": 0.8333333333333334,
   "PKM,VEGFB": 0.08928571428571429,
   "PLK2,RHOA": 0.9090909090909091,
   "PLK2,RNF213": 0.8695652173913043,
   "PLK2,THBS1": 0.36363636363636365,
   "PLK2,VEGFB": 0.0847457627118644,
   "RHOA,RNF213": 0.37037037037037035,
   "RHOA,THBS1": 0.7142857142857143,
   "RHOA,VEGFB": 0.8333333333333334,
   "RNF213,THBS1": 0.06622516556291391,
   "RNF213,VEGFB": 0.8,
   "THBS1,VEGFB": 0.2631578947368421
  },
  "GO_REGULATION_OF_CELL_MIGRATION_INVOLVED_IN_SPROUTING_ANGIOGENESIS": {
   "ABL1,ANXA1": 0.3508771929824561,
   "ABL1,CIB1": 0.17857142857142858,
   "ABL1,FBXW7": 0.1282051282051282,
   "ABL1,FGFBP1": 0.29850746268656714,
   "ABL1,HDAC7": 0.1092896174863388,
   "ABL1,HMOX1": 0.5,
   "ABL1,ITGB1BP1": 0.37735849056603776,
   "ABL1,KLF4": 0.6451612903225806,
   "ABL1,NOTCH1": 0.625,
   "ABL1,NRP1": 0.15873015873015872,
   "ABL1,PLK2": 0.40816326530612246,
   "ABL1,RHOA": 0.6666666666666666,
   "ABL1,THBS1": 1.0,
   "ABL1,VEGFA": 0.9523809523809523,
   "ANXA1,CIB1": 0.02,
   "ANXA1,FBXW7": 0.5555555555555556,
   "ANXA1,FGFBP1": 0.001,
   "ANXA1,HDAC7": 0.4444444444444444,
   "ANXA1,HMOX1": 0.17391304347826086,
   "ANXA1,ITGB1BP1": 0.06779661016949153,
   "ANXA1,KLF4": 0.0711743772241993,
   "ANXA1,NOTCH1": 0.20408163265306123,
   "ANXA1,NRP1": 0.03225806451612903,
   "ANXA1,PLK2": 0.2564102564102564,
   "ANXA1,RHOA": 0.46511627906976744,
   "ANXA1,THBS1": 0.005,
   "ANXA1,VEGFA": 0.20202020202020202,
   "CIB1,FBXW7": 0.9090909090909091,
   "CIB1,FGFBP1": 0.3448275862068966,
   "CIB1,HDAC7": 0.7407407407407407,
   "CIB1,HMOX1": 0.3389830508474576,
   "CIB1,ITGB1BP1": 0.2898550724637681,
   "CIB1,KLF4": 0.5882352941176471,
   "CIB1,NOTCH1": 0.8,
   "CIB1,NRP1": 0.136986301369863,
   "CIB1,PLK2": 0.012,
   "CIB1,RHOA": 0.6060606060606061,
   "CIB1,THBS1": 0.11494252873563218,
   "CIB1,VEGFA": 0.4444444444444444,
   "FBXW7,FGFBP1": 0.17094017094017094,
   "FBXW7,HDAC7": 0.5882352941176471,
   "FBXW7,HMOX1": 0.7692307692307693,
   "FBXW7,ITGB1BP1": 0.3225806451612903,
   "FBXW7,KLF4": 0.7142857142857143,
   "FBXW7,NOTCH1": 0.5714285714285714,
   "FBXW7,NRP1": 0.21739130434782608,
   "FBXW7,PLK2": 0.47619047619047616,
   "FBXW7,RHOA": 0.20408163265306123,
   "FBXW7,THBS1": 0.29411764705882354,
   "FBXW7,VEGFA": 0.8333333333333334,
   "FGFBP1,HDAC7": 0.5128205128205128,
   "FGFBP1,HMOX1": 0.46511627906976744,
   "FGFBP1,ITGB1BP1": 0.625,
   "FGFBP1,KLF4": 0.15873015873015872,
   "FGFBP1,NOTCH1": 0.21739130434782608,
   "FGFBP1,NRP1": 0.06802721088435375,
   "FGFBP1,PLK2": 0.47619047619047616,
   "FGFBP1,RHOA": 0.46511627906976744,
   "FGFBP1,THBS1": 0.9090909090909091,
   "FGFBP1,VEGFA": 0.09302325581395349,
   "HDAC7,HMOX1": 0.04914004914004914,
   "HDAC7,ITGB1BP1": 0.32786885245901637,
   "HDAC7,KLF4": 0.11560693641618497,
   "HDAC7,NOTCH1": 1.0,
   "HDAC7,NRP1": 0.8,
   "HDAC7,PLK2": 0.7142857142857143,
   "HDAC7,RHOA": 0.015,
   "HDAC7,THBS1": 0.6451612903225806,
   "HDAC7,VEGFA": 0.5128205128205128,
   "HMOX1,ITGB1BP1": 0.46511627906976744,
   "HMOX1,KLF4": 0.425531914893617,
   "HMOX1,NOTCH1": 0.18518518518518517,
   "HMOX1,NRP1": 0.02249718785151856,
   "HMOX1,PLK2": 0.32786885245901637,
   "HMOX1,RHOA": 0.5128205128205128,
   "HMOX1,THBS1": 0.425531914893617,
   "HMOX1,VEGFA": 0.6451612903225806,
   "ITGB1BP1,KLF4": 0.29850746268656714,
   "ITGB1BP1,NOTCH1": 0.9090909090909091,
   "ITGB1BP1,NRP1": 0.14184397163120568,
   "ITGB1BP1,PLK2": 0.007,
   "ITGB1BP1,RHOA": 0.011,
   "ITGB1BP1,THBS1": 0.6451612903225806,
   "ITGB1BP1,VEGFA": 0.30303030303030304,
   "KLF4,NOTCH1": 0.16260162601626016,
   "KLF4,NRP1": 0.47619047619047616,
   "KLF4,PLK2": 0.3389830508474576,
   "KLF4,RHOA": 0.38461538461538464,
   "KLF4,THBS1": 0.6666666666666666,
   "KLF4,VEGFA": 0.5882352941176471,
   "NOTCH1,NRP1": 0.6666666666666666,
   "NOTCH1,PLK2": 0.36363636363636365,
   "NOTCH1,RHOA": 0.4878048780487805,
   "NOTCH1,THBS1": 0.5405405405405406,
   "NOTCH1,VEGFA": 0.04065040650406504,
   "NRP1,PLK2": 0.19607843137254902,
   "NRP1,RHOA": 0.5555555555555556,
   "NRP1,THBS1": 0.625,
   "NRP1,VEGFA": 0.08849557522123894,
   "PLK2,RHOA": 0.9090909090909091,
   "PLK2,THBS1": 0.36363636363636365,
   "PLK2,VEGFA": 0.38461538461538464,
   "RHOA,THBS1": 0.7142857142857143,
   "RHOA,VEGFA": 0.9523809523809523,
   "THBS1,VEGFA": 0.7407407407407407
  },
  "GO_POSITIVE_REGULATION_OF_SPROUTING_ANGIOGENESIS": {
   "ABL1,ANXA1": 0.3508771929824561,
   "ABL1,CIB1": 0.17857142857142858,
   "ABL1,FGFBP1": 0.29850746268656714,
   "ABL1,HDAC7": 0.1092896174863388,
   "ABL1,HMOX1": 0.5,
   "ABL1,ITGA5": 0.1834862385321101,
   "ABL1,JAK1": 0.8695652173913043,
   "ABL1,JMJD8": 0.8695652173913043,
   "ABL1,KLF4": 0.6451612903225806,
   "ABL1,MAP3K3": 0.3389830508474576,
   "ABL1,NRP1": 0.15873015873015872,
   "ABL1,PKM": 0.8695652173913043,
   "ABL1,PLK2": 0.40816326530612246,
   "ABL1,VEGFA": 0.9523809523809523,
   "ANXA1,CIB1": 0.02,
   "ANXA1,FGFBP1": 0.001,
   "ANXA1,HDAC7": 0.4444444444444444,
   "ANXA1,HMOX1": 0.17391304347826086,
   "ANXA1,ITGA5": 0.037243947858473,
   "ANXA1,JAK1": 0.2857142857142857,
   "ANXA1,JMJD8": 0.4166666666666667,
   "ANXA1,KLF4": 0.0711743772241993,
   "ANXA1,MAP3K3": 0.43478260869565216,
   "ANXA1,NRP1": 0.03225806451612903,
   "ANXA1,PKM": 0.6451612903225806,
   "ANXA1,PLK2": 0.2564102564102564,
   "ANXA1,VEGFA": 0.20202020202020202,
   "CIB1,FGFBP1": 0.3448275862068966,
   "CIB1,HDAC7": 0.7407407407407407,
   "CIB1,HMOX1": 0.3389830508474576,
   "CIB1,ITGA5": 0.04987531172069826,
   "CIB1,JAK1": 0.19047619047619047,
   "CIB1,JMJD8": 0.2127659574468085,
   "CIB1,KLF4": 0.5882352941176471,
   "CIB1,MAP3K3": 0.7692307692307693,
   "CIB1,NRP1": 0.136986301369863,
   "CIB1,PKM": 1.0,
   "CIB1,PLK2": 0.012,
   "CIB1,VEGFA": 0.4444444444444444,
   "FGFBP1,HDAC7": 0.5128205128205128,
   "FGFBP1,HMOX1": 0.46511627906976744,
   "FGFBP1,ITGA5": 0.9090909090909091,
   "FGFBP1,JAK1": 0.7407407407407407,
   "FGFBP1,JMJD8": 0.8333333333333334,
   "FGFBP1,KLF4": 0.15873015873015872,
   "FGFBP1,MAP3K3": 0.23529411764705882,
   "FGFBP1,NRP1": 0.06802721088435375,
   "FGFBP1,PKM": 0.3333333333333333,
   "FGFBP1,PLK2": 0.47619047619047616,
   "FGFBP1,VEGFA": 0.09302325581395349,
   "HDAC7,HMOX1": 0.04914004914004914,
   "HDAC7,ITGA5": 0.23809523809523808,
   "HDAC7,JAK1": 0.8695652173913043,
   "HDAC7,JMJD8": 0.25316455696202533,
   "HDAC7,KLF4": 0.11560693641618497,
   "HDAC7,MAP3K3": 1.0,
   "HDAC7,NRP1": 0.8,
   "HDAC7,PKM": 0.5555555555555556,
   "HDAC7,PLK2": 0.7142857142857143,
   "HDAC7,VEGFA": 0.5128205128205128,
   "HMOX1,ITGA5": 0.9523809523809523,
   "HMOX1,JAK1": 0.4878048780487805,
   "HMOX1,JMJD8": 0.625,
   "HMOX1,KLF4": 0.425531914893617,
   "HMOX1,MAP3K3": 0.3125,
   "HMOX1,NRP1": 0.02249718785151856,
   "HMOX1,PKM": 0.15267175572519084,
   "HMOX1,PLK2": 0.32786885245901637,
   "HMOX1,VEGFA": 0.6451612903225806,
   "ITGA5,JAK1": 0.8695652173913043,
   "ITGA5,JMJD8": 0.18518518518518517,
   "ITGA5,KLF4": 0.6451612903225806,
   "ITGA5,MAP3K3": 0.1360544217687075,
   "ITGA5,NRP1": 0.5263157894736842,
   "ITGA5,PKM": 0.7407407407407407,
   "ITGA5,PLK2": 0.47619047619047616,
   "ITGA5,VEGFA": 0.12121212121212122,
   "JAK1,JMJD8": 0.10869565217391304,
   "JAK1,KLF4": 0.9523809523809523,
   "JAK1,MAP3K3": 0.7407407407407407,
   "JAK1,NRP1": 0.006,
   "JAK1,PKM": 0.21052631578947367,
   "JAK1,PLK2": 0.9090909090909091,
   "JAK1,VEGFA": 0.9523809523809523,
   "JMJD8,KLF4": 0.7407407407407407,
   "JMJD8,MAP3K3": 0.06097560975609756,
   "JMJD8,NRP1": 0.8695652173913043,
   "JMJD8,PKM": 0.19047619047619047,
   "JMJD8,PLK2": 0.8,
   "JMJD8,VEGFA": 0.39215686274509803,
   "KLF4,MAP3K3": 0.8333333333333334,
   "KLF4,NRP1": 0.47619047619047616,
   "KLF4,PKM": 0.8695652173913043,
   "KLF4,PLK2": 0.3389830508474576,
   "KLF4,VEGFA": 0.5882352941176471,
   "MAP3K3,NRP1": 0.136986301369863,
   "MAP3K3,PKM": 0.5882352941176471,
   "MAP3K3,PLK2": 0.7142857142857143,
   "MAP3K3,VEGFA": 0.29850746268656714,
   "NRP1,PKM": 0.8,
   "NRP1,PLK2": 0.19607843137254902,
   "NRP1,VEGFA": 0.08849557522123894,
   "PKM,PLK2": 0.3389830508474576,
   "PKM,VEGFA": 0.027586206896551724,
   "PLK2,VEGFA": 0.38461538461538464
  },
  "GO_REGULATION_OF_SPROUTING_ANGIOGENESIS": {
   "ANXA1,CIB1": 0.02,
   "ANXA1,EPN1": 0.8333333333333334,
   "ANXA1,FGFBP1": 0.001,
   "ANXA1,GLUL": 0.014,
   "ANXA1,HMOX1": 0.17391304347826086,
   "ANXA1,ITGA5": 0.037243947858473,
   "ANXA1,ITGB1BP1": 0.06779661016949153,
   "ANXA1,JAK1": 0.2857142857142857,
   "ANXA1,KLF4": 0.0711743772241993,
   "ANXA1,NOTCH1": 0.20408163265306123,
   "ANXA1,PKM": 0.6451612903225806,
   "ANXA1,PLK2": 0.2564102564102564,
   "ANXA1,RHOA": 0.46511627906976744,
   "ANXA1,THBS1": 0.005,
   "CIB1,EPN1": 0.5555555555555556,
   "CIB1,FGFBP1": 0.3448275862068966,
   "CIB1,GLUL": 0.37735849056603776,
   "CIB1,HMOX1": 0.3389830508474576,
   "CIB1,ITGA5": 0.04987531172069826,
   "CIB1,ITGB1BP1": 0.2898550724637681,
   "CIB1,JAK1": 0.19047619047619047,
   "CIB1,KLF4": 0.5882352941176471,
   "CIB1,NOTCH1": 0.8,
   "CIB1,PKM": 1.0,
   "CIB1,PLK2": 0.012,
   "CIB1,RHOA": 0.6060606060606061,
   "CIB1,THBS1": 0.11494252873563218,
   "EPN1,FGFBP1": 0.8,
   "EPN1,GLUL": 0.3333333333333333,
   "EPN1,HMOX1": 0.9090909090909091,
   "EPN1,ITGA5": 0.05649717514124294,
   "EPN1,ITGB1BP1": 0.043010752688172046,
   "EPN1,JAK1": 0.07142857142857142,
   "EPN1,KLF4": 0.17391304347826086,
   "EPN1,NOTCH1": 0.08163265306122448,
   "EPN1,PKM": 0.6451612903225806,
   "EPN1,PLK2": 0.30303030303030304,
   "EPN1,RHOA": 0.5882352941176471,
   "EPN1,THBS1": 0.06535947712418301,
   "FGFBP1,GLUL": 0.04219409282700422,
   "FGFBP1,HMOX1": 0.46511627906976744,
   "FGFBP1,ITGA5": 0.9090909090909091,
   "FGFBP1,ITGB1BP1": 0.625,
   "FGFBP1,JAK1": 0.7407407407407407,
   "FGFBP1,KLF4": 0.15873015873015872,
   "FGFBP1,NOTCH1": 0.21739130434782608,
   "FGFBP1,PKM": 0.3333333333333333,
   "FGFBP1,PLK2": 0.47619047619047616,
   "FGFBP1,RHOA": 0.46511627906976744,
   "FGFBP1,THBS1": 0.9090909090909091,
   "GLUL,HMOX1": 0.46511627906976744,
   "GLUL,ITGA5": 0.07220216606498195,
   "GLUL,ITGB1BP1": 0.9523809523809523,
   "GLUL,JAK1": 0.47619047619047616,
   "GLUL,KLF4": 0.05555555555555555,
   "GLUL,NOTCH1": 0.05181347150259067,
   "GLUL,PKM": 0.8333333333333334,
   "GLUL,PLK2": 0.4166666666666667,
   "GLUL,RHOA": 0.40816326530612246,
   "GLUL,THBS1": 0.4,
   "HMOX1,ITGA5": 0.9523809523809523,
   "HMOX1,ITGB1BP1": 0.46511627906976744,
   "HMOX1,JAK1": 0.4878048780487805,
   "HMOX1,KLF4": 0.425531914893617,
   "HMOX1,NOTCH1": 0.18518518518518517,
   "HMOX1,PKM": 0.15267175572519084,
   "HMOX1,PLK2": 0.32786885245901637,
   "HMOX1,RHOA": 0.5128205128205128,
   "HMOX1,THBS1": 0.425531914893617,
   "ITGA5,ITGB1BP1": 0.5882352941176471,
   "ITGA5,JAK1": 0.8695652173913043,
   "ITGA5,KLF4": 0.6451612903225806,
   "ITGA5,NOTCH1": 1.0,
   "ITGA5,PKM": 0.7407407407407407,
   "ITGA5,PLK2": 0.47619047619047616,
   "ITGA5,RHOA": 0.26666666666666666,
   "ITGA5,THBS1": 0.5882352941176471,
   "ITGB1BP1,JAK1": 0.6666666666666666,
   "ITGB1BP1,KLF4": 0.29850746268656714,
   "ITGB1BP1,NOTCH1": 0.9090909090909091,
   "ITGB1BP1,PKM": 0.3508771929824561,
   "ITGB1BP1,PLK2": 0.007,
   "ITGB1BP1,RHOA": 0.011,
   "ITGB1BP1,THBS1": 0.6451612903225806,
   "JAK1,KLF4": 0.9523809523809523,
   "JAK1,NOTCH1": 0.5882352941176471,
   "JAK1,PKM": 0.21052631578947367,
   "JAK1,PLK2": 0.9090909090909091,
   "JAK1,RHOA": 0.5714285714285714,
   "JAK1,THBS1": 0.8333333333333334,
   "KLF4,NOTCH1": 0.16260162601626016,
   "KLF4,PKM": 0.8695652173913043,
   "KLF4,PLK2": 0.3389830508474576,
   "KLF4,RHOA": 0.38461538461538464,
   "KLF4,THBS1": 0.6666666666666666,
   "NOTCH1,PKM": 0.006,
   "NOTCH1,PLK2": 0.36363636363636365,
   "NOTCH1,RHOA": 0.4878048780487805,
   "NOTCH1,THBS1": 0.5405405405405406,
   "PKM,PLK2": 0.3389830508474576,
   "PKM,RHOA": 0.5882352941176471,
   "PKM,THBS1": 0.8333333333333334,
   "PLK2,RHOA": 0.9090909090909091,
   "PLK2,THBS1": 0.36363636363636365,
   "RHOA,THBS1": 0.7142857142857143
  },
  "GO_POSITIVE_REGULATION_OF_CELL_MIGRATION_INVOLVED_IN_SPROUTING_ANGIOGENESIS": {
   "ABL1,ANXA1": 0.3508771929824561,
   "ABL1,CIB1": 0.17857142857142858,
   "ABL1,FGFBP1": 0.29850746268656714,
   "ABL1,HDAC7": 0.1092896174863388,
   "ABL1,HMOX1": 0.5,
   "ABL1,MAP3K3": 0.3389830508474576,
   "ABL1,NRP1": 0.15873015873015872,
   "ABL1,PIK3C2A": 1.0,
   "ABL1,PLK2": 0.40816326530612246,
   "ABL1,VEGFA": 0.9523809523809523,
   "ANXA1,CIB1": 0.02,
   "ANXA1,FGFBP1": 0.001,
   "ANXA1,HDAC7": 0.4444444444444444,
   "ANXA1,HMOX1": 0.17391304347826086,
   "ANXA1,MAP3K3": 0.43478260869565216,
   "ANXA1,NRP1": 0.03225806451612903,
   "ANXA1,PIK3C2A": 0.3125,
   "ANXA1,PLK2": 0.2564102564102564,
   "ANXA1,VEGFA": 0.20202020202020202,
   "CIB1,FGFBP1": 0.3448275862068966,
   "CIB1,HDAC7": 0.7407407407407407,
   "CIB1,HMOX1": 0.3389830508474576,
   "CIB1,MAP3K3": 0.7692307692307693,
   "CIB1,NRP1": 0.136986301369863,
   "CIB1,PIK3C2A": 1.0,
   "CIB1,PLK2": 0.012,
   "CIB1,VEGFA": 0.4444444444444444,
   "FGFBP1,HDAC7": 0.5128205128205128,
   "FGFBP1,HMOX1": 0.46511627906976744,
   "FGFBP1,MAP3K3": 0.23529411764705882,
   "FGFBP1,NRP1": 0.06802721088435375,
   "FGFBP1,PIK3C2A": 0.14084507042253522,
   "FGFBP1,PLK2": 0.47619047619047616,
   "FGFBP1,VEGFA": 0.09302325581395349,
   "HDAC7,HMOX1": 0.04914004914004914,
   "HDAC7,MAP3K3": 1.0,
   "HDAC7,NRP1": 0.8,
   "HDAC7,PIK3C2A": 0.39215686274509803,
   "HDAC7,PLK2": 0.7142857142857143,
   "HDAC7,VEGFA": 0.5128205128205128,
   "HMOX1,MAP3K3": 0.3125,
   "HMOX1,NRP1": 0.02249718785151856,
   "HMOX1,PIK3C2A": 0.46511627906976744,
   "HMOX1,PLK2": 0.32786885245901637,
   "HMOX1,VEGFA": 0.6451612903225806,
   "MAP3K3,NRP1": 0.136986301369863,
   "MAP3K3,PIK3C2A": 0.8,
   "MAP3K3,PLK2": 0.7142857142857143,
   "MAP3K3,VEGFA": 0.29850746268656714,
   "NRP1,PIK3C2A": 0.5882352941176471,
   "NRP1,PLK2": 0.19607843137254902,
   "NRP1,VEGFA": 0.08849557522123894,
   "PIK3C2A,PLK2": 0.6060606060606061,
   "PIK3C2A,VEGFA": 0.08333333333333333,
   "PLK2,VEGFA": 0.38461538461538464
  }
 },
 "gene_set_to_keep_clusts": {
  "GO_CELL_MIGRATION_INVOLVED_IN_SPROUTING_ANGIOGENESIS": [
   1,
   2,
   3,
   4,
   5,
   6,
   7,
   8
  ],
  "GO_SPROUTING_ANGIOGENESIS": [
   1,
   2,
   3,
   4,
   5,
   6,
   7,
   8
  ],
  "GO_NEGATIVE_REGULATION_OF_SPROUTING_ANGIOGENESIS": [
   1,
   2,
   3,
   4,
   5,
   6,
   7,
   8
  ],
  "GO_LYMPHANGIOGENESIS": [
   1,
   2,
   3,
   4,
   5,
   6,
   7,
   8
  ],
  "GO_REGULATION_OF_CELL_MIGRATION_INVOLVED_IN_SPROUTING_ANGIOGENESIS": [
   1,
   2,
   3,
   4,
   5,
   6,
   7,
   8
  ],
  "GO_POSITIVE_REGULATION_OF_SPROUTING_ANGIOGENESIS": [
   1,
   2,
   3,
   4,
   5,
   6,
   7,
   8
  ],
  "GO_ANGIOGENESIS_INVOLVED_IN_WOUND_HEALING": [
   1,
   2,
   4,
   5,
   6,
   7,
   8
  ],
  "GO_REGULATION_OF_SPROUTING_ANGIOGENESIS": [
   1,
   2,
   3,
   4,
   5,
   6,
   7,
   8
  ],
  "GO_BLOOD_VESSEL_ENDOTHELIAL_CELL_PROLIFERATION_INVOLVED_IN_SPROUTING_ANGIOGENESIS": [
   1,
   2,
   3,
   4,
   5,
   6,
   7,
   8
  ],
  "GO_POSITIVE_REGULATION_OF_CELL_MIGRATION_INVOLVED_IN_SPROUTING_ANGIOGENESIS": [
   1,
   2,
   3,
   4,
   5,
   6,
   7,
   8
  ],
  "GO_NEGATIVE_REGULATION_OF_CELL_MIGRATION_INVOLVED_IN_SPROUTING_ANGIOGENESIS": [
   1,
   2,
   3,
   4,
   5,
   6,
   7,
   8
  ]
 }
}